README.md
setup.cfg
setup.py
instagram_basic_display/InstagramBasicDisplay.py
instagram_basic_display/InstagramBasicDisplayException.py
instagram_basic_display/__init__.py
instagram_basic_display.egg-info/PKG-INFO
instagram_basic_display.egg-info/SOURCES.txt
instagram_basic_display.egg-info/dependency_links.txt
instagram_basic_display.egg-info/requires.txt
instagram_basic_display.egg-info/top_level.txt